ltn_imp/__init__.py
ltn_imp/automation/data_loaders.py
ltn_imp/automation/knowledge_base.py
ltn_imp/automation/network_factory.py
ltn_imp/fuzzy_operators/__init__.py
ltn_imp/fuzzy_operators/aggregators.py
ltn_imp/fuzzy_operators/connectives.py
ltn_imp/fuzzy_operators/diagrams/aggregators_and_quantifiers.puml
ltn_imp/fuzzy_operators/diagrams/connective.puml
ltn_imp/fuzzy_operators/predicates.py
ltn_imp/fuzzy_operators/quantifiers.py
ltn_imp/main.py
ltn_imp/parsing/__init__.py
ltn_imp/parsing/ancillary_modules.py
ltn_imp/parsing/expressions.py
ltn_imp/parsing/fol_parser.ebnf
ltn_imp/parsing/parser.py
ltn_imp/parsing/parser_generator.py
ltn_imp/visitor.py
ekuru_ltn-3.2.0.dist-info/LICENSE
ekuru_ltn-3.2.0.dist-info/METADATA
ekuru_ltn-3.2.0.dist-info/WHEEL
ekuru_ltn-3.2.0.dist-info/RECORD
