Metadata-Version: 2.3
Name: ekuru_ltn
Version: 3.2.0
Summary: A parser for FOL that utilizes NLTK Logic Module to parse and fuzzify FOL rules.
License: Apache 2.0
Author: Emre Kuru
Author-email: emre.kuru@ozu.edu.tr
Requires-Python: >=3.11.0,<4.0.0
Classifier: License :: Other/Proprietary License
Classifier: Programming Language :: Python :: 3
Classifier: Programming Language :: Python :: 3.11
Classifier: Programming Language :: Python :: 3.12
Classifier: Programming Language :: Python :: 3.13
Requires-Dist: hyperopt (>=0.2.7,<0.3.0)
Requires-Dist: nbconvert (>=7.16.4,<8.0.0)
Requires-Dist: nbformat (>=5.10.4,<6.0.0)
Requires-Dist: pykeen (>=1.10.2,<2.0.0)
Requires-Dist: pyparsing (>=3.1.2,<4.0.0)
Requires-Dist: pyyaml (>=6.0.2,<7.0.0)
Requires-Dist: seaborn (>=0.13.2,<0.14.0)
Requires-Dist: setuptools (>=78.0.0,<79.0.0)
Requires-Dist: tatsu (>=5.12.1,<6.0.0)
Requires-Dist: torch (>=2.3.1,<3.0.0)
Requires-Dist: torchviz (>=0.0.3,<0.0.4)
Requires-Dist: ucimlrepo (>=0.0.7,<0.0.8)
